hadloc/__init__.py
hadloc/__main__.py
hadloc/error.py
hadloc/utils.py
hadloc/writer.py
hadloc/assembler/__init__.py
hadloc/assembler/assembler.py
hadloc/assembler/codewriter.py
hadloc/assembler/label_encoder.py
hadloc/assembler/parser.py
hadloc/assembler/tokenizer.py
hadloc/compiler/__init__.py
hadloc/compiler/compiler.py
hadloc/compiler/parser.py
hadloc/compiler/tokenizer.py
hadloc/emulator/__init__.py
hadloc/emulator/disassembler.py
hadloc/emulator/display.py
hadloc/emulator/emulator.py
hadloc/emulator/word.py
hadloc/grammar/__init__.py
hadloc/grammar/abstract_syntax_tree.py
hadloc/grammar/grammar.py
hadloc/grammar/parser.py
hadloc/grammar/token_list.py
hadloc/text_utils/__init__.py
hadloc/text_utils/code.py
hadloc/text_utils/code_object.py
hadloc/text_utils/positioned_string.py
hadloc/translator/__init__.py
hadloc/translator/codewriter.py
hadloc/translator/parser.py
hadloc/translator/parser_errors.json
hadloc/translator/tokenizer.py
hadloc/translator/translator.py
hadloc-0.1.1.dist-info/LICENSE
hadloc-0.1.1.dist-info/METADATA
hadloc-0.1.1.dist-info/WHEEL
hadloc-0.1.1.dist-info/entry_points.txt
hadloc-0.1.1.dist-info/top_level.txt
hadloc-0.1.1.dist-info/RECORD
