Metadata-Version: 2.1
Name: hadloc
Version: 0.1.1
Summary: Command line tool to build, emulate and load programs for the HaDLOC 8-bit computer
Home-page: https://github.com/nicholasprowse/HADLoC
Author: Nic Prowse
License: GNU General Public License v3.0
Classifier: Programming Language :: Python :: 3.11
Classifier: Operating System :: OS Independent
Classifier: Development Status :: 3 - Alpha
Classifier: Environment :: Console
Classifier: Environment :: Console :: Curses
Classifier: License :: OSI Approved :: GNU General Public License v3 (GPLv3)
Classifier: Natural Language :: English
Classifier: Topic :: Software Development :: Assemblers
Classifier: Topic :: Software Development :: Compilers
Classifier: Topic :: System :: Emulators
Requires-Python: >=3.11
License-File: LICENSE
Requires-Dist: pyserial (~=3.5)
